abundant_sdk/PYPI_UPLOAD_GUIDE.md
abundant_sdk/README.md
abundant_sdk/__init__.py
abundant_sdk/client.py
abundant_sdk/models.py
abundant_sdk-0.2.4.dist-info/METADATA
abundant_sdk-0.2.4.dist-info/WHEEL
abundant_sdk-0.2.4.dist-info/licenses/LICENSE
abundant_sdk-0.2.4.dist-info/RECORD
