Metadata-Version: 2.4
Name: abundant-sdk
Version: 0.2.4
Summary: Python SDK for the Abundant Environment API - simulation environments for RL agent training
Project-URL: Homepage, https://github.com/your-org/simulation-env-api
Project-URL: Documentation, https://github.com/your-org/simulation-env-api/tree/main/docs
Project-URL: Repository, https://github.com/your-org/simulation-env-api
Project-URL: Issues, https://github.com/your-org/simulation-env-api/issues
Author-email: Meji Abidoye <pfbyjy@gmail.com>
License: Apache-2.0
License-File: LICENSE
Keywords: api,automation,reinforcement-learning,salesforce,simulation
Classifier: Development Status :: 4 - Beta
Classifier: Intended Audience :: Developers
Classifier: License :: OSI Approved :: Apache Software License
Classifier: Programming Language :: Python :: 3
Classifier: Programming Language :: Python :: 3.8
Classifier: Programming Language :: Python :: 3.9
Classifier: Programming Language :: Python :: 3.10
Classifier: Programming Language :: Python :: 3.11
Classifier: Programming Language :: Python :: 3.12
Classifier: Programming Language :: Python :: 3.13
Classifier: Topic :: Scientific/Engineering :: Artificial Intelligence
Classifier: Topic :: Software Development :: Libraries :: Python Modules
Requires-Python: >=3.8
Requires-Dist: httpx>=0.27.2
Requires-Dist: pydantic>=2.0.0
Provides-Extra: dev
Requires-Dist: black>=24.10.0; extra == 'dev'
Requires-Dist: mypy>=1.13.0; extra == 'dev'
Requires-Dist: pre-commit>=4.2.0; extra == 'dev'
Requires-Dist: pytest-asyncio>=0.24.0; extra == 'dev'
Requires-Dist: pytest-cov>=6.0.0; extra == 'dev'
Requires-Dist: pytest-mock>=3.14.0; extra == 'dev'
Requires-Dist: pytest>=8.3.3; extra == 'dev'
Requires-Dist: ruff>=0.7.0; extra == 'dev'
